ebel/__init__.py
ebel/__main__.py
ebel/cache.py
ebel/cli.py
ebel/config.py
ebel/constants.py
ebel/database.py
ebel/defaults.py
ebel/errors.py
ebel/grammar/__init__.py
ebel/grammar/grammar_bel_2.bnf
ebel/grammar/grammar_bel_2_1.bnf
ebel/grammar/grammar_belns_belanno_1__2.bnf
ebel/grammar/README.md
ebel/manager/__init__.py
ebel/manager/models.py
ebel/manager/molecular_interaction.py
ebel/manager/orientdb/__init__.py
ebel/manager/orientdb/biodbs/__init__.py
ebel/manager/orientdb/biodbs/bel.py
ebel/manager/orientdb/biodbs/biogrid.py
ebel/manager/orientdb/biodbs/chebi.py
ebel/manager/orientdb/biodbs/clinical_trials.py
ebel/manager/orientdb/biodbs/clinvar.py
ebel/manager/orientdb/biodbs/disgenet.py
ebel/manager/orientdb/biodbs/drugbank.py
ebel/manager/orientdb/biodbs/ensembl.py
ebel/manager/orientdb/biodbs/expression_atlas.py
ebel/manager/orientdb/biodbs/gwas_catalog.py
ebel/manager/orientdb/biodbs/hgnc.py
ebel/manager/orientdb/biodbs/intact.py
ebel/manager/orientdb/biodbs/iuphar.py
ebel/manager/orientdb/biodbs/kegg.py
ebel/manager/orientdb/biodbs/mirtarbase.py
ebel/manager/orientdb/biodbs/ncbi.py
ebel/manager/orientdb/biodbs/nsides.py
ebel/manager/orientdb/biodbs/pathway_commons.py
ebel/manager/orientdb/biodbs/protein_atlas.py
ebel/manager/orientdb/biodbs/reactome.py
ebel/manager/orientdb/biodbs/stringdb.py
ebel/manager/orientdb/biodbs/uniprot.py
ebel/manager/orientdb/constants.py
ebel/manager/orientdb/importer.py
ebel/manager/orientdb/odb_defaults.py
ebel/manager/orientdb/odb_meta.py
ebel/manager/orientdb/odb_structure.py
ebel/manager/orientdb/urls.py
ebel/manager/rdbms/__init__.py
ebel/manager/rdbms/models/__init__.py
ebel/manager/rdbms/models/biogrid.py
ebel/manager/rdbms/models/chebi.py
ebel/manager/rdbms/models/clinical_trials_gov.py
ebel/manager/rdbms/models/clinvar.py
ebel/manager/rdbms/models/disgenet.py
ebel/manager/rdbms/models/drugbank.py
ebel/manager/rdbms/models/ensembl.py
ebel/manager/rdbms/models/expression_atlas.py
ebel-1.0.37.dist-info/entry_points.txt
ebel-1.0.37.dist-info/LICENSE
ebel-1.0.37.dist-info/METADATA
ebel-1.0.37.dist-info/WHEEL
ebel-1.0.37.dist-info/RECORD
