Metadata-Version: 2.1
Name: ebel
Version: 1.0.37
Summary: e(BE:L) - validation and extension of BEL networks.
Home-page: https://github.com/e-bel/ebel
License: MIT
Keywords: Biomedical Database,Biological Expression Lnaguage,Graph Database
Author: Bruce Schultz
Author-email: bruce.schultz@scai.fraunhofer.de
Maintainer: Christian Ebeling
Maintainer-email: christian.ebeling@scai.fraunhofer.de
Requires-Python: >=3.9,<4.0
Classifier: Development Status :: 5 - Production/Stable
Classifier: Environment :: Console
Classifier: Intended Audience :: Developers
Classifier: Intended Audience :: Science/Research
Classifier: License :: OSI Approved :: MIT License
Classifier: Operating System :: OS Independent
Classifier: Programming Language :: Python
Classifier: Programming Language :: Python :: 3
Classifier: Programming Language :: Python :: 3.9
Classifier: Programming Language :: Python :: 3.10
Classifier: Programming Language :: Python :: 3.11
Classifier: Programming Language :: Python :: 3 :: Only
Classifier: Topic :: Scientific/Engineering :: Bio-Informatics
Provides-Extra: docs
Requires-Dist: GitPython (>=3.1.14,<4.0.0)
Requires-Dist: PyMySQL (>=1.0.2,<2.0.0)
Requires-Dist: SQLAlchemy-Utils (>=0.37.7,<0.38.0)
Requires-Dist: click (>=7.1.2,<8.0.0)
Requires-Dist: connexion[swagger-ui] (>=2.14.1,<3.0.0)
Requires-Dist: cryptography (>=3.4.7,<4.0.0)
Requires-Dist: flask (>=2.0.1,<3.0.0)
Requires-Dist: flask_cors (>=3.0.10,<4.0.0)
Requires-Dist: graphviz (==0.20)
Requires-Dist: lark-parser (>=0.11.2,<0.12.0)
Requires-Dist: lxml (>=4.6.5,<5.0.0)
Requires-Dist: mkdocstrings[python] (>=0.18,<0.19)
Requires-Dist: openpyxl (>=3.0.10,<4.0.0)
Requires-Dist: pandas (>=1.2.4,<2.0.0)
Requires-Dist: pyorientdb (>=1.0.0,<2.0.0)
Requires-Dist: requests (>=2.25.1,<3.0.0)
Requires-Dist: sqlalchemy (>=1.4.46,<2.0.0)
Requires-Dist: tqdm (>=4.59.0,<5.0.0)
Requires-Dist: xlrd (>=2.0.1,<3.0.0)
Requires-Dist: xlsxwriter (>=1.3.8,<2.0.0)
Requires-Dist: xlwt (>=1.3.0,<2.0.0)
Requires-Dist: xmltodict (>=0.12.0,<0.13.0)
Project-URL: Documentation, https://ebel.readthedocs.io/en/latest/
Project-URL: Issues, https://github.com/e-bel/ebel/issues
Project-URL: Repository, https://github.com/e-bel/ebel
